LICENSE
MANIFEST.in
README.md
setup.py
coupons/__init__.py
coupons/admin.py
coupons/forms.py
coupons/models.py
coupons/settings.py
coupons/locale/de/LC_MESSAGES/django.mo
coupons/locale/de/LC_MESSAGES/django.po
coupons/migrations/0001_initial.py
coupons/migrations/0002_coupon_valid_until.py
coupons/migrations/0003_auto_20150416_0617.py
coupons/migrations/__init__.py
coupons/south_migrations/0001_initial.py
coupons/south_migrations/0002_auto__add_field_coupon_valid_until.py
coupons/south_migrations/0003_auto__add_campaign__add_field_coupon_campaign.py
coupons/south_migrations/__init__.py
coupons/templates/admin/generate_coupons.html
coupons/tests/__init__.py
coupons/tests/settings.py
coupons/tests/test_forms.py
coupons/tests/test_models.py
django_coupons.egg-info/PKG-INFO
django_coupons.egg-info/SOURCES.txt
django_coupons.egg-info/dependency_links.txt
django_coupons.egg-info/top_level.txt