Metadata-Version: 1.1
Name: django-coupons
Version: 1.1.0
Summary: A reuseable Django application for coupon gereration and handling.
Home-page: https://github.com/byteweaver/django-coupons
Author: byteweaver
Author-email: contact@byteweaver.net
License: Copyright (c) 2013, byteweaver
